{
  "a_comp_cor_00": {
    "CumulativeVarianceExplained": 0.0254966469,
    "Mask": "combined",
    "Method": "aCompCor",
    "Retained": true,
    "SingularValue": 68.5253052079,
    "VarianceExplained": 0.0254966469
  },
  "a_comp_cor_01": {
    "CumulativeVarianceExplained": 0.0502205348,
    "Mask": "combined",
    "Method": "aCompCor",
    "Retained": true,
    "SingularValue": 67.478874013,
    "VarianceExplained": 0.0247238879
  },
  "a_comp_cor_02": {
    "CumulativeVarianceExplained": 0.0720094525,
    "Mask": "combined",
    "Method": "aCompCor",
    "Retained": true,
    "SingularValue": 63.3471781027,
    "VarianceExplained": 0.0217889177
  },
  "a_comp_cor_03": {
    "CumulativeVarianceExplained": 0.0921556757,
    "Mask": "combined",
    "Method": "aCompCor",
    "Retained": true,
    "SingularValue": 60.9124775676,
    "VarianceExplained": 0.0201462232
  },
  "a_comp_cor_04": {
    "CumulativeVarianceExplained": 0.1116343835,
    "Mask": "combined",
    "Method": "aCompCor",
    "Retained": true,
    "SingularValue": 59.8948547753,
    "VarianceExplained": 0.0194787079
  },
  "a_comp_cor_05": {
    "CumulativeVarianceExplained": 0.128479119,
    "Mask": "combined",
    "Method": "aCompCor",
    "Retained": true,
    "SingularValue": 55.6982488173,
    "VarianceExplained": 0.0168447354
  },
  "a_comp_cor_06": {
    "CumulativeVarianceExplained": 0.1436426912,
    "Mask": "combined",
    "Method": "aCompCor",
    "Retained": true,
    "SingularValue": 52.8457671425,
    "VarianceExplained": 0.0151635723
  },
  "a_comp_cor_07": {
    "CumulativeVarianceExplained": 0.1584064754,
    "Mask": "combined",
    "Method": "aCompCor",
    "Retained": true,
    "SingularValue": 52.1444736369,
    "VarianceExplained": 0.0147637842
  },
  "a_comp_cor_08": {
    "CumulativeVarianceExplained": 0.1723294219,
    "Mask": "combined",
    "Method": "aCompCor",
    "Retained": true,
    "SingularValue": 50.6378223585,
    "VarianceExplained": 0.0139229465
  },
  "a_comp_cor_09": {
    "CumulativeVarianceExplained": 0.1858036294,
    "Mask": "combined",
    "Method": "aCompCor",
    "Retained": true,
    "SingularValue": 49.8151061073,
    "VarianceExplained": 0.0134742075
  },
  "a_comp_cor_10": {
    "CumulativeVarianceExplained": 0.1991548455,
    "Mask": "combined",
    "Method": "aCompCor",
    "Retained": true,
    "SingularValue": 49.5872308432,
    "VarianceExplained": 0.0133512161
  },
  "a_comp_cor_11": {
    "CumulativeVarianceExplained": 0.2123659335,
    "Mask": "combined",
    "Method": "aCompCor",
    "Retained": true,
    "SingularValue": 49.3263224017,
    "VarianceExplained": 0.013211088
  },
  "a_comp_cor_12": {
    "CumulativeVarianceExplained": 0.225441906,
    "Mask": "combined",
    "Method": "aCompCor",
    "Retained": true,
    "SingularValue": 49.0734333116,
    "VarianceExplained": 0.0130759725
  },
  "a_comp_cor_13": {
    "CumulativeVarianceExplained": 0.2384632566,
    "Mask": "combined",
    "Method": "aCompCor",
    "Retained": true,
    "SingularValue": 48.9708295771,
    "VarianceExplained": 0.0130213507
  },
  "a_comp_cor_14": {
    "CumulativeVarianceExplained": 0.2511803717,
    "Mask": "combined",
    "Method": "aCompCor",
    "Retained": true,
    "SingularValue": 48.3953622434,
    "VarianceExplained": 0.0127171151
  },
  "a_comp_cor_15": {
    "CumulativeVarianceExplained": 0.26383264,
    "Mask": "combined",
    "Method": "aCompCor",
    "Retained": true,
    "SingularValue": 48.2718162819,
    "VarianceExplained": 0.0126522683
  },
  "a_comp_cor_16": {
    "CumulativeVarianceExplained": 0.2762570326,
    "Mask": "combined",
    "Method": "aCompCor",
    "Retained": true,
    "SingularValue": 47.8351374679,
    "VarianceExplained": 0.0124243926
  },
  "a_comp_cor_17": {
    "CumulativeVarianceExplained": 0.2886089131,
    "Mask": "combined",
    "Method": "aCompCor",
    "Retained": true,
    "SingularValue": 47.6953440608,
    "VarianceExplained": 0.0123518806
  },
  "a_comp_cor_18": {
    "CumulativeVarianceExplained": 0.3008578231,
    "Mask": "combined",
    "Method": "aCompCor",
    "Retained": true,
    "SingularValue": 47.4961234278,
    "VarianceExplained": 0.0122489099
  },
  "a_comp_cor_19": {
    "CumulativeVarianceExplained": 0.3129616391,
    "Mask": "combined",
    "Method": "aCompCor",
    "Retained": true,
    "SingularValue": 47.2139789721,
    "VarianceExplained": 0.0121038161
  },
  "a_comp_cor_20": {
    "CumulativeVarianceExplained": 0.3248986239,
    "Mask": "combined",
    "Method": "aCompCor",
    "Retained": true,
    "SingularValue": 46.8874661073,
    "VarianceExplained": 0.0119369847
  },
  "a_comp_cor_21": {
    "CumulativeVarianceExplained": 0.336763411,
    "Mask": "combined",
    "Method": "aCompCor",
    "Retained": true,
    "SingularValue": 46.7454581016,
    "VarianceExplained": 0.0118647872
  },
  "a_comp_cor_22": {
    "CumulativeVarianceExplained": 0.34848067,
    "Mask": "combined",
    "Method": "aCompCor",
    "Retained": true,
    "SingularValue": 46.4539297556,
    "VarianceExplained": 0.011717259
  },
  "a_comp_cor_23": {
    "CumulativeVarianceExplained": 0.3600300733,
    "Mask": "combined",
    "Method": "aCompCor",
    "Retained": true,
    "SingularValue": 46.1199913341,
    "VarianceExplained": 0.0115494033
  },
  "a_comp_cor_24": {
    "CumulativeVarianceExplained": 0.3714204319,
    "Mask": "combined",
    "Method": "aCompCor",
    "Retained": true,
    "SingularValue": 45.8013356344,
    "VarianceExplained": 0.0113903586
  },
  "a_comp_cor_25": {
    "CumulativeVarianceExplained": 0.3827489846,
    "Mask": "combined",
    "Method": "aCompCor",
    "Retained": true,
    "SingularValue": 45.6769038405,
    "VarianceExplained": 0.0113285527
  },
  "a_comp_cor_26": {
    "CumulativeVarianceExplained": 0.3939073568,
    "Mask": "combined",
    "Method": "aCompCor",
    "Retained": true,
    "SingularValue": 45.3325205207,
    "VarianceExplained": 0.0111583722
  },
  "a_comp_cor_27": {
    "CumulativeVarianceExplained": 0.4049432252,
    "Mask": "combined",
    "Method": "aCompCor",
    "Retained": true,
    "SingularValue": 45.0829887945,
    "VarianceExplained": 0.0110358684
  },
  "a_comp_cor_28": {
    "CumulativeVarianceExplained": 0.4158814402,
    "Mask": "combined",
    "Method": "aCompCor",
    "Retained": true,
    "SingularValue": 44.8830819647,
    "VarianceExplained": 0.0109382149
  },
  "a_comp_cor_29": {
    "CumulativeVarianceExplained": 0.4267570074,
    "Mask": "combined",
    "Method": "aCompCor",
    "Retained": true,
    "SingularValue": 44.754365321,
    "VarianceExplained": 0.0108755672
  },
  "a_comp_cor_30": {
    "CumulativeVarianceExplained": 0.4375388589,
    "Mask": "combined",
    "Method": "aCompCor",
    "Retained": true,
    "SingularValue": 44.5611220189,
    "VarianceExplained": 0.0107818515
  },
  "a_comp_cor_31": {
    "CumulativeVarianceExplained": 0.4482677991,
    "Mask": "combined",
    "Method": "aCompCor",
    "Retained": true,
    "SingularValue": 44.4516468435,
    "VarianceExplained": 0.0107289401
  },
  "a_comp_cor_32": {
    "CumulativeVarianceExplained": 0.4589520855,
    "Mask": "combined",
    "Method": "aCompCor",
    "Retained": true,
    "SingularValue": 44.3590467255,
    "VarianceExplained": 0.0106842864
  },
  "a_comp_cor_33": {
    "CumulativeVarianceExplained": 0.4695493645,
    "Mask": "combined",
    "Method": "aCompCor",
    "Retained": true,
    "SingularValue": 44.1780588966,
    "VarianceExplained": 0.0105972791
  },
  "a_comp_cor_34": {
    "CumulativeVarianceExplained": 0.47994342,
    "Mask": "combined",
    "Method": "aCompCor",
    "Retained": true,
    "SingularValue": 43.7524077816,
    "VarianceExplained": 0.0103940554
  },
  "a_comp_cor_35": {
    "CumulativeVarianceExplained": 0.4903001832,
    "Mask": "combined",
    "Method": "aCompCor",
    "Retained": true,
    "SingularValue": 43.6738489894,
    "VarianceExplained": 0.0103567632
  },
  "a_comp_cor_36": {
    "CumulativeVarianceExplained": 0.5005712675,
    "Mask": "combined",
    "Method": "aCompCor",
    "Retained": true,
    "SingularValue": 43.4928222441,
    "VarianceExplained": 0.0102710843
  },
  "aroma_motion_1": {
    "CSFFraction": 0.01,
    "EdgeFraction": 0.52,
    "HighFrequencyContent": 0.06,
    "MaximumRpCorrelation": 0.88,
    "Method": {
      "Name": "ICA-AROMA",
      "Version": "0.4.5"
    },
    "ModelVarianceExplained": 0.1365147014,
    "MotionNoise": true,
    "TotalVarianceExplained": 0.0942297518
  },
  "aroma_motion_10": {
    "CSFFraction": 0.03,
    "EdgeFraction": 0.68,
    "HighFrequencyContent": 0.1,
    "MaximumRpCorrelation": 0.77,
    "Method": {
      "Name": "ICA-AROMA",
      "Version": "0.4.5"
    },
    "ModelVarianceExplained": 0.0522357014,
    "MotionNoise": true,
    "TotalVarianceExplained": 0.0360558762
  },
  "aroma_motion_11": {
    "CSFFraction": 0.04,
    "EdgeFraction": 0.85,
    "HighFrequencyContent": 0.22,
    "MaximumRpCorrelation": 0.68,
    "Method": {
      "Name": "ICA-AROMA",
      "Version": "0.4.5"
    },
    "ModelVarianceExplained": 0.050246467,
    "MotionNoise": true,
    "TotalVarianceExplained": 0.0346828002
  },
  "aroma_motion_12": {
    "CSFFraction": 0.19,
    "EdgeFraction": 0.72,
    "HighFrequencyContent": 0.62,
    "MaximumRpCorrelation": 0.37,
    "Method": {
      "Name": "ICA-AROMA",
      "Version": "0.4.5"
    },
    "ModelVarianceExplained": 0.0476723279,
    "MotionNoise": true,
    "TotalVarianceExplained": 0.0329059917
  },
  "aroma_motion_13": {
    "CSFFraction": 0.02,
    "EdgeFraction": 0.44,
    "HighFrequencyContent": 0.18,
    "MaximumRpCorrelation": 0.29,
    "Method": {
      "Name": "ICA-AROMA",
      "Version": "0.4.5"
    },
    "ModelVarianceExplained": 0.0460910643,
    "MotionNoise": false,
    "TotalVarianceExplained": 0.0318145189
  },
  "aroma_motion_14": {
    "CSFFraction": 0.02,
    "EdgeFraction": 0.55,
    "HighFrequencyContent": 0.18,
    "MaximumRpCorrelation": 0.65,
    "Method": {
      "Name": "ICA-AROMA",
      "Version": "0.4.5"
    },
    "ModelVarianceExplained": 0.0430841058,
    "MotionNoise": true,
    "TotalVarianceExplained": 0.0297389553
  },
  "aroma_motion_15": {
    "CSFFraction": 0.27,
    "EdgeFraction": 0.56,
    "HighFrequencyContent": 0.58,
    "MaximumRpCorrelation": 0.36,
    "Method": {
      "Name": "ICA-AROMA",
      "Version": "0.4.5"
    },
    "ModelVarianceExplained": 0.0423689013,
    "MotionNoise": true,
    "TotalVarianceExplained": 0.0292452828
  },
  "aroma_motion_16": {
    "CSFFraction": 0.02,
    "EdgeFraction": 0.57,
    "HighFrequencyContent": 0.14,
    "MaximumRpCorrelation": 0.6,
    "Method": {
      "Name": "ICA-AROMA",
      "Version": "0.4.5"
    },
    "ModelVarianceExplained": 0.0420898318,
    "MotionNoise": true,
    "TotalVarianceExplained": 0.0290526541
  },
  "aroma_motion_17": {
    "CSFFraction": 0.23,
    "EdgeFraction": 0.68,
    "HighFrequencyContent": 0.52,
    "MaximumRpCorrelation": 0.34,
    "Method": {
      "Name": "ICA-AROMA",
      "Version": "0.4.5"
    },
    "ModelVarianceExplained": 0.0402760993,
    "MotionNoise": true,
    "TotalVarianceExplained": 0.027800719
  },
  "aroma_motion_2": {
    "CSFFraction": 0.01,
    "EdgeFraction": 0.52,
    "HighFrequencyContent": 0.08,
    "MaximumRpCorrelation": 0.47,
    "Method": {
      "Name": "ICA-AROMA",
      "Version": "0.4.5"
    },
    "ModelVarianceExplained": 0.0757295142,
    "MotionNoise": false,
    "TotalVarianceExplained": 0.052272563
  },
  "aroma_motion_3": {
    "CSFFraction": 0.01,
    "EdgeFraction": 0.86,
    "HighFrequencyContent": 0.16,
    "MaximumRpCorrelation": 0.88,
    "Method": {
      "Name": "ICA-AROMA",
      "Version": "0.4.5"
    },
    "ModelVarianceExplained": 0.0718829172,
    "MotionNoise": true,
    "TotalVarianceExplained": 0.0496174359
  },
  "aroma_motion_4": {
    "CSFFraction": 0.05,
    "EdgeFraction": 0.79,
    "HighFrequencyContent": 0.2,
    "MaximumRpCorrelation": 0.56,
    "Method": {
      "Name": "ICA-AROMA",
      "Version": "0.4.5"
    },
    "ModelVarianceExplained": 0.0632027002,
    "MotionNoise": true,
    "TotalVarianceExplained": 0.0436258857
  },
  "aroma_motion_5": {
    "CSFFraction": 0.03,
    "EdgeFraction": 0.3,
    "HighFrequencyContent": 0.14,
    "MaximumRpCorrelation": 0.3,
    "Method": {
      "Name": "ICA-AROMA",
      "Version": "0.4.5"
    },
    "ModelVarianceExplained": 0.061728001,
    "MotionNoise": false,
    "TotalVarianceExplained": 0.0426079694
  },
  "aroma_motion_6": {
    "CSFFraction": 0.01,
    "EdgeFraction": 0.59,
    "HighFrequencyContent": 0.12,
    "MaximumRpCorrelation": 0.45,
    "Method": {
      "Name": "ICA-AROMA",
      "Version": "0.4.5"
    },
    "ModelVarianceExplained": 0.0589535216,
    "MotionNoise": false,
    "TotalVarianceExplained": 0.0406928752
  },
  "aroma_motion_7": {
    "CSFFraction": 0.01,
    "EdgeFraction": 0.47,
    "HighFrequencyContent": 0.1,
    "MaximumRpCorrelation": 0.58,
    "Method": {
      "Name": "ICA-AROMA",
      "Version": "0.4.5"
    },
    "ModelVarianceExplained": 0.0573885382,
    "MotionNoise": false,
    "TotalVarianceExplained": 0.0396126399
  },
  "aroma_motion_8": {
    "CSFFraction": 0.03,
    "EdgeFraction": 0.62,
    "HighFrequencyContent": 0.1,
    "MaximumRpCorrelation": 0.52,
    "Method": {
      "Name": "ICA-AROMA",
      "Version": "0.4.5"
    },
    "ModelVarianceExplained": 0.0554599256,
    "MotionNoise": true,
    "TotalVarianceExplained": 0.0382814084
  },
  "aroma_motion_9": {
    "CSFFraction": 0.13,
    "EdgeFraction": 0.74,
    "HighFrequencyContent": 0.62,
    "MaximumRpCorrelation": 0.47,
    "Method": {
      "Name": "ICA-AROMA",
      "Version": "0.4.5"
    },
    "ModelVarianceExplained": 0.0550756819,
    "MotionNoise": true,
    "TotalVarianceExplained": 0.0380161828
  },
  "c_comp_cor_00": {
    "CumulativeVarianceExplained": 0.1009894844,
    "Mask": "CSF",
    "Method": "aCompCor",
    "Retained": true,
    "SingularValue": 42.4577707361,
    "VarianceExplained": 0.1009894844
  },
  "c_comp_cor_01": {
    "CumulativeVarianceExplained": 0.1824691456,
    "Mask": "CSF",
    "Method": "aCompCor",
    "Retained": true,
    "SingularValue": 38.1367533033,
    "VarianceExplained": 0.0814796612
  },
  "c_comp_cor_02": {
    "CumulativeVarianceExplained": 0.253881363,
    "Mask": "CSF",
    "Method": "aCompCor",
    "Retained": true,
    "SingularValue": 35.703054233,
    "VarianceExplained": 0.0714122175
  },
  "c_comp_cor_03": {
    "CumulativeVarianceExplained": 0.3075228157,
    "Mask": "CSF",
    "Method": "aCompCor",
    "Retained": true,
    "SingularValue": 30.9434957564,
    "VarianceExplained": 0.0536414526
  },
  "c_comp_cor_04": {
    "CumulativeVarianceExplained": 0.3548117688,
    "Mask": "CSF",
    "Method": "aCompCor",
    "Retained": true,
    "SingularValue": 29.0535335657,
    "VarianceExplained": 0.0472889531
  },
  "c_comp_cor_05": {
    "CumulativeVarianceExplained": 0.3885338919,
    "Mask": "CSF",
    "Method": "aCompCor",
    "Retained": true,
    "SingularValue": 24.5344634924,
    "VarianceExplained": 0.0337221232
  },
  "c_comp_cor_06": {
    "CumulativeVarianceExplained": 0.4187198401,
    "Mask": "CSF",
    "Method": "aCompCor",
    "Retained": true,
    "SingularValue": 23.2124788581,
    "VarianceExplained": 0.0301859482
  },
  "c_comp_cor_07": {
    "CumulativeVarianceExplained": 0.4448236013,
    "Mask": "CSF",
    "Method": "aCompCor",
    "Retained": true,
    "SingularValue": 21.5859245043,
    "VarianceExplained": 0.0261037612
  },
  "c_comp_cor_08": {
    "CumulativeVarianceExplained": 0.4696982001,
    "Mask": "CSF",
    "Method": "aCompCor",
    "Retained": true,
    "SingularValue": 21.0715825061,
    "VarianceExplained": 0.0248745988
  },
  "c_comp_cor_09": {
    "CumulativeVarianceExplained": 0.4931910595,
    "Mask": "CSF",
    "Method": "aCompCor",
    "Retained": true,
    "SingularValue": 20.4779769655,
    "VarianceExplained": 0.0234928594
  },
  "c_comp_cor_10": {
    "CumulativeVarianceExplained": 0.5136979117,
    "Mask": "CSF",
    "Method": "aCompCor",
    "Retained": true,
    "SingularValue": 19.1323629466,
    "VarianceExplained": 0.0205068522
  },
  "csf": {
    "Method": "Mean"
  },
  "csf_wm": {
    "Method": "Mean"
  },
  "global_signal": {
    "Method": "Mean"
  },
  "t_comp_cor_00": {
    "CumulativeVarianceExplained": 0.1495585926,
    "Method": "tCompCor",
    "Retained": true,
    "SingularValue": 128.1027578796,
    "VarianceExplained": 0.1495585926
  },
  "t_comp_cor_01": {
    "CumulativeVarianceExplained": 0.2863387479,
    "Method": "tCompCor",
    "Retained": true,
    "SingularValue": 122.5079692745,
    "VarianceExplained": 0.1367801553
  },
  "t_comp_cor_02": {
    "CumulativeVarianceExplained": 0.4086855126,
    "Method": "tCompCor",
    "Retained": true,
    "SingularValue": 115.8641392432,
    "VarianceExplained": 0.1223467648
  },
  "t_comp_cor_03": {
    "CumulativeVarianceExplained": 0.4814684103,
    "Method": "tCompCor",
    "Retained": true,
    "SingularValue": 89.365001207,
    "VarianceExplained": 0.0727828976
  },
  "t_comp_cor_04": {
    "CumulativeVarianceExplained": 0.5293523283,
    "Method": "tCompCor",
    "Retained": true,
    "SingularValue": 72.4849150347,
    "VarianceExplained": 0.047883918
  },
  "tcompcor": {
    "Method": "Mean"
  },
  "w_comp_cor_00": {
    "CumulativeVarianceExplained": 0.0230620677,
    "Mask": "WM",
    "Method": "aCompCor",
    "Retained": true,
    "SingularValue": 58.8453011435,
    "VarianceExplained": 0.0230620677
  },
  "w_comp_cor_01": {
    "CumulativeVarianceExplained": 0.0410762922,
    "Mask": "WM",
    "Method": "aCompCor",
    "Retained": true,
    "SingularValue": 52.008035982,
    "VarianceExplained": 0.0180142245
  },
  "w_comp_cor_02": {
    "CumulativeVarianceExplained": 0.058673906,
    "Mask": "WM",
    "Method": "aCompCor",
    "Retained": true,
    "SingularValue": 51.4031293574,
    "VarianceExplained": 0.0175976138
  },
  "w_comp_cor_03": {
    "CumulativeVarianceExplained": 0.0750974929,
    "Mask": "WM",
    "Method": "aCompCor",
    "Retained": true,
    "SingularValue": 49.6588519078,
    "VarianceExplained": 0.0164235869
  },
  "w_comp_cor_04": {
    "CumulativeVarianceExplained": 0.0908342724,
    "Mask": "WM",
    "Method": "aCompCor",
    "Retained": true,
    "SingularValue": 48.6094378299,
    "VarianceExplained": 0.0157367795
  },
  "w_comp_cor_05": {
    "CumulativeVarianceExplained": 0.1059279767,
    "Mask": "WM",
    "Method": "aCompCor",
    "Retained": true,
    "SingularValue": 47.6058788609,
    "VarianceExplained": 0.0150937043
  },
  "w_comp_cor_06": {
    "CumulativeVarianceExplained": 0.1208193717,
    "Mask": "WM",
    "Method": "aCompCor",
    "Retained": true,
    "SingularValue": 47.2857585792,
    "VarianceExplained": 0.014891395
  },
  "w_comp_cor_07": {
    "CumulativeVarianceExplained": 0.1352615456,
    "Mask": "WM",
    "Method": "aCompCor",
    "Retained": true,
    "SingularValue": 46.5670742425,
    "VarianceExplained": 0.0144421738
  },
  "w_comp_cor_08": {
    "CumulativeVarianceExplained": 0.1496275441,
    "Mask": "WM",
    "Method": "aCompCor",
    "Retained": true,
    "SingularValue": 46.4441027422,
    "VarianceExplained": 0.0143659985
  },
  "w_comp_cor_09": {
    "CumulativeVarianceExplained": 0.1638262748,
    "Mask": "WM",
    "Method": "aCompCor",
    "Retained": true,
    "SingularValue": 46.1729293917,
    "VarianceExplained": 0.0141987307
  },
  "w_comp_cor_10": {
    "CumulativeVarianceExplained": 0.1777847147,
    "Mask": "WM",
    "Method": "aCompCor",
    "Retained": true,
    "SingularValue": 45.7805608788,
    "VarianceExplained": 0.0139584399
  },
  "w_comp_cor_11": {
    "CumulativeVarianceExplained": 0.1917082508,
    "Mask": "WM",
    "Method": "aCompCor",
    "Retained": true,
    "SingularValue": 45.723286711,
    "VarianceExplained": 0.0139235361
  },
  "w_comp_cor_12": {
    "CumulativeVarianceExplained": 0.2052971026,
    "Mask": "WM",
    "Method": "aCompCor",
    "Retained": true,
    "SingularValue": 45.1704116838,
    "VarianceExplained": 0.0135888518
  },
  "w_comp_cor_13": {
    "CumulativeVarianceExplained": 0.218827197,
    "Mask": "WM",
    "Method": "aCompCor",
    "Retained": true,
    "SingularValue": 45.0726489691,
    "VarianceExplained": 0.0135300945
  },
  "w_comp_cor_14": {
    "CumulativeVarianceExplained": 0.2322495395,
    "Mask": "WM",
    "Method": "aCompCor",
    "Retained": true,
    "SingularValue": 44.8928135851,
    "VarianceExplained": 0.0134223424
  },
  "w_comp_cor_15": {
    "CumulativeVarianceExplained": 0.2454148048,
    "Mask": "WM",
    "Method": "aCompCor",
    "Retained": true,
    "SingularValue": 44.460820908,
    "VarianceExplained": 0.0131652654
  },
  "w_comp_cor_16": {
    "CumulativeVarianceExplained": 0.2584824729,
    "Mask": "WM",
    "Method": "aCompCor",
    "Retained": true,
    "SingularValue": 44.2957149759,
    "VarianceExplained": 0.0130676681
  },
  "w_comp_cor_17": {
    "CumulativeVarianceExplained": 0.2713049428,
    "Mask": "WM",
    "Method": "aCompCor",
    "Retained": true,
    "SingularValue": 43.87817064,
    "VarianceExplained": 0.0128224699
  },
  "w_comp_cor_18": {
    "CumulativeVarianceExplained": 0.2840538182,
    "Mask": "WM",
    "Method": "aCompCor",
    "Retained": true,
    "SingularValue": 43.7520700602,
    "VarianceExplained": 0.0127488754
  },
  "w_comp_cor_19": {
    "CumulativeVarianceExplained": 0.2967346693,
    "Mask": "WM",
    "Method": "aCompCor",
    "Retained": true,
    "SingularValue": 43.6351899236,
    "VarianceExplained": 0.0126808511
  },
  "w_comp_cor_20": {
    "CumulativeVarianceExplained": 0.3091907564,
    "Mask": "WM",
    "Method": "aCompCor",
    "Retained": true,
    "SingularValue": 43.2467509284,
    "VarianceExplained": 0.012456087
  },
  "w_comp_cor_21": {
    "CumulativeVarianceExplained": 0.3215142336,
    "Mask": "WM",
    "Method": "aCompCor",
    "Retained": true,
    "SingularValue": 43.0159285884,
    "VarianceExplained": 0.0123234773
  },
  "w_comp_cor_22": {
    "CumulativeVarianceExplained": 0.3336147271,
    "Mask": "WM",
    "Method": "aCompCor",
    "Retained": true,
    "SingularValue": 42.6249820135,
    "VarianceExplained": 0.0121004935
  },
  "w_comp_cor_23": {
    "CumulativeVarianceExplained": 0.3456430532,
    "Mask": "WM",
    "Method": "aCompCor",
    "Retained": true,
    "SingularValue": 42.497684191,
    "VarianceExplained": 0.0120283261
  },
  "w_comp_cor_24": {
    "CumulativeVarianceExplained": 0.3575691125,
    "Mask": "WM",
    "Method": "aCompCor",
    "Retained": true,
    "SingularValue": 42.3166374306,
    "VarianceExplained": 0.0119260593
  },
  "w_comp_cor_25": {
    "CumulativeVarianceExplained": 0.3693078327,
    "Mask": "WM",
    "Method": "aCompCor",
    "Retained": true,
    "SingularValue": 41.9829589429,
    "VarianceExplained": 0.0117387202
  },
  "w_comp_cor_26": {
    "CumulativeVarianceExplained": 0.3809600747,
    "Mask": "WM",
    "Method": "aCompCor",
    "Retained": true,
    "SingularValue": 41.8280305791,
    "VarianceExplained": 0.011652242
  },
  "w_comp_cor_27": {
    "CumulativeVarianceExplained": 0.3924458969,
    "Mask": "WM",
    "Method": "aCompCor",
    "Retained": true,
    "SingularValue": 41.5282577926,
    "VarianceExplained": 0.0114858221
  },
  "w_comp_cor_28": {
    "CumulativeVarianceExplained": 0.4038420393,
    "Mask": "WM",
    "Method": "aCompCor",
    "Retained": true,
    "SingularValue": 41.3658166701,
    "VarianceExplained": 0.0113961424
  },
  "w_comp_cor_29": {
    "CumulativeVarianceExplained": 0.4150938996,
    "Mask": "WM",
    "Method": "aCompCor",
    "Retained": true,
    "SingularValue": 41.103124273,
    "VarianceExplained": 0.0112518603
  },
  "w_comp_cor_30": {
    "CumulativeVarianceExplained": 0.4262960857,
    "Mask": "WM",
    "Method": "aCompCor",
    "Retained": true,
    "SingularValue": 41.0122937101,
    "VarianceExplained": 0.011202186
  },
  "w_comp_cor_31": {
    "CumulativeVarianceExplained": 0.4373847641,
    "Mask": "WM",
    "Method": "aCompCor",
    "Retained": true,
    "SingularValue": 40.803983381,
    "VarianceExplained": 0.0110886784
  },
  "w_comp_cor_32": {
    "CumulativeVarianceExplained": 0.4483440016,
    "Mask": "WM",
    "Method": "aCompCor",
    "Retained": true,
    "SingularValue": 40.5651267921,
    "VarianceExplained": 0.0109592375
  },
  "w_comp_cor_33": {
    "CumulativeVarianceExplained": 0.4592863981,
    "Mask": "WM",
    "Method": "aCompCor",
    "Retained": true,
    "SingularValue": 40.5339466978,
    "VarianceExplained": 0.0109423965
  },
  "w_comp_cor_34": {
    "CumulativeVarianceExplained": 0.4700609085,
    "Mask": "WM",
    "Method": "aCompCor",
    "Retained": true,
    "SingularValue": 40.2217944102,
    "VarianceExplained": 0.0107745105
  },
  "w_comp_cor_35": {
    "CumulativeVarianceExplained": 0.4807066178,
    "Mask": "WM",
    "Method": "aCompCor",
    "Retained": true,
    "SingularValue": 39.9806608017,
    "VarianceExplained": 0.0106457092
  },
  "w_comp_cor_36": {
    "CumulativeVarianceExplained": 0.4913224296,
    "Mask": "WM",
    "Method": "aCompCor",
    "Retained": true,
    "SingularValue": 39.9244805689,
    "VarianceExplained": 0.0106158118
  },
  "w_comp_cor_37": {
    "CumulativeVarianceExplained": 0.501877331,
    "Mask": "WM",
    "Method": "aCompCor",
    "Retained": true,
    "SingularValue": 39.8097782826,
    "VarianceExplained": 0.0105549014
  },
  "white_matter": {
    "Method": "Mean"
  }
}