{
  "a_comp_cor_00": {
    "CumulativeVarianceExplained": 0.0307690011,
    "Mask": "combined",
    "Method": "aCompCor",
    "Retained": true,
    "SingularValue": 93.6561423611,
    "VarianceExplained": 0.0307690011
  },
  "a_comp_cor_01": {
    "CumulativeVarianceExplained": 0.058080293,
    "Mask": "combined",
    "Method": "aCompCor",
    "Retained": true,
    "SingularValue": 88.2369907302,
    "VarianceExplained": 0.0273112919
  },
  "a_comp_cor_02": {
    "CumulativeVarianceExplained": 0.077426438,
    "Mask": "combined",
    "Method": "aCompCor",
    "Retained": true,
    "SingularValue": 74.2637347019,
    "VarianceExplained": 0.019346145
  },
  "a_comp_cor_03": {
    "CumulativeVarianceExplained": 0.0931975823,
    "Mask": "combined",
    "Method": "aCompCor",
    "Retained": true,
    "SingularValue": 67.0519123748,
    "VarianceExplained": 0.0157711443
  },
  "a_comp_cor_04": {
    "CumulativeVarianceExplained": 0.1084435884,
    "Mask": "combined",
    "Method": "aCompCor",
    "Retained": true,
    "SingularValue": 65.926134392,
    "VarianceExplained": 0.0152460061
  },
  "a_comp_cor_05": {
    "CumulativeVarianceExplained": 0.1234493794,
    "Mask": "combined",
    "Method": "aCompCor",
    "Retained": true,
    "SingularValue": 65.404708154,
    "VarianceExplained": 0.0150057909
  },
  "a_comp_cor_06": {
    "CumulativeVarianceExplained": 0.1376182103,
    "Mask": "combined",
    "Method": "aCompCor",
    "Retained": true,
    "SingularValue": 63.5545393381,
    "VarianceExplained": 0.0141688309
  },
  "a_comp_cor_07": {
    "CumulativeVarianceExplained": 0.1516598201,
    "Mask": "combined",
    "Method": "aCompCor",
    "Retained": true,
    "SingularValue": 63.268569823,
    "VarianceExplained": 0.0140416098
  },
  "a_comp_cor_08": {
    "CumulativeVarianceExplained": 0.1655102567,
    "Mask": "combined",
    "Method": "aCompCor",
    "Retained": true,
    "SingularValue": 62.8364004069,
    "VarianceExplained": 0.0138504366
  },
  "a_comp_cor_09": {
    "CumulativeVarianceExplained": 0.1786427545,
    "Mask": "combined",
    "Method": "aCompCor",
    "Retained": true,
    "SingularValue": 61.1861650576,
    "VarianceExplained": 0.0131324977
  },
  "a_comp_cor_10": {
    "CumulativeVarianceExplained": 0.1914285978,
    "Mask": "combined",
    "Method": "aCompCor",
    "Retained": true,
    "SingularValue": 60.3732083154,
    "VarianceExplained": 0.0127858433
  },
  "a_comp_cor_11": {
    "CumulativeVarianceExplained": 0.2040913048,
    "Mask": "combined",
    "Method": "aCompCor",
    "Retained": true,
    "SingularValue": 60.0817875344,
    "VarianceExplained": 0.012662707
  },
  "a_comp_cor_12": {
    "CumulativeVarianceExplained": 0.2165680121,
    "Mask": "combined",
    "Method": "aCompCor",
    "Retained": true,
    "SingularValue": 59.6388911357,
    "VarianceExplained": 0.0124767073
  },
  "a_comp_cor_13": {
    "CumulativeVarianceExplained": 0.2288207462,
    "Mask": "combined",
    "Method": "aCompCor",
    "Retained": true,
    "SingularValue": 59.1011690244,
    "VarianceExplained": 0.0122527341
  },
  "a_comp_cor_14": {
    "CumulativeVarianceExplained": 0.2410132522,
    "Mask": "combined",
    "Method": "aCompCor",
    "Retained": true,
    "SingularValue": 58.9557345946,
    "VarianceExplained": 0.012192506
  },
  "a_comp_cor_15": {
    "CumulativeVarianceExplained": 0.2530300377,
    "Mask": "combined",
    "Method": "aCompCor",
    "Retained": true,
    "SingularValue": 58.5293528207,
    "VarianceExplained": 0.0120167856
  },
  "a_comp_cor_16": {
    "CumulativeVarianceExplained": 0.2649795802,
    "Mask": "combined",
    "Method": "aCompCor",
    "Retained": true,
    "SingularValue": 58.3653649318,
    "VarianceExplained": 0.0119495425
  },
  "a_comp_cor_17": {
    "CumulativeVarianceExplained": 0.2767457712,
    "Mask": "combined",
    "Method": "aCompCor",
    "Retained": true,
    "SingularValue": 57.9158603875,
    "VarianceExplained": 0.0117661909
  },
  "a_comp_cor_18": {
    "CumulativeVarianceExplained": 0.2884111756,
    "Mask": "combined",
    "Method": "aCompCor",
    "Retained": true,
    "SingularValue": 57.6672797535,
    "VarianceExplained": 0.0116654044
  },
  "a_comp_cor_19": {
    "CumulativeVarianceExplained": 0.2999847426,
    "Mask": "combined",
    "Method": "aCompCor",
    "Retained": true,
    "SingularValue": 57.4398347503,
    "VarianceExplained": 0.011573567
  },
  "a_comp_cor_20": {
    "CumulativeVarianceExplained": 0.311428617,
    "Mask": "combined",
    "Method": "aCompCor",
    "Retained": true,
    "SingularValue": 57.1170946678,
    "VarianceExplained": 0.0114438744
  },
  "a_comp_cor_21": {
    "CumulativeVarianceExplained": 0.3228005659,
    "Mask": "combined",
    "Method": "aCompCor",
    "Retained": true,
    "SingularValue": 56.9373193901,
    "VarianceExplained": 0.0113719489
  },
  "a_comp_cor_22": {
    "CumulativeVarianceExplained": 0.334081387,
    "Mask": "combined",
    "Method": "aCompCor",
    "Retained": true,
    "SingularValue": 56.7087301584,
    "VarianceExplained": 0.0112808211
  },
  "a_comp_cor_23": {
    "CumulativeVarianceExplained": 0.3452516414,
    "Mask": "combined",
    "Method": "aCompCor",
    "Retained": true,
    "SingularValue": 56.4301362429,
    "VarianceExplained": 0.0111702544
  },
  "a_comp_cor_24": {
    "CumulativeVarianceExplained": 0.3563752769,
    "Mask": "combined",
    "Method": "aCompCor",
    "Retained": true,
    "SingularValue": 56.3122578454,
    "VarianceExplained": 0.0111236355
  },
  "a_comp_cor_25": {
    "CumulativeVarianceExplained": 0.367418035,
    "Mask": "combined",
    "Method": "aCompCor",
    "Retained": true,
    "SingularValue": 56.1071675786,
    "VarianceExplained": 0.0110427581
  },
  "a_comp_cor_26": {
    "CumulativeVarianceExplained": 0.3783191524,
    "Mask": "combined",
    "Method": "aCompCor",
    "Retained": true,
    "SingularValue": 55.7461751405,
    "VarianceExplained": 0.0109011174
  },
  "a_comp_cor_27": {
    "CumulativeVarianceExplained": 0.3891338257,
    "Mask": "combined",
    "Method": "aCompCor",
    "Retained": true,
    "SingularValue": 55.5247060872,
    "VarianceExplained": 0.0108146733
  },
  "a_comp_cor_28": {
    "CumulativeVarianceExplained": 0.3998857786,
    "Mask": "combined",
    "Method": "aCompCor",
    "Retained": true,
    "SingularValue": 55.3634626046,
    "VarianceExplained": 0.010751953
  },
  "a_comp_cor_29": {
    "CumulativeVarianceExplained": 0.4105707123,
    "Mask": "combined",
    "Method": "aCompCor",
    "Retained": true,
    "SingularValue": 55.1906465079,
    "VarianceExplained": 0.0106849337
  },
  "a_comp_cor_30": {
    "CumulativeVarianceExplained": 0.4211753223,
    "Mask": "combined",
    "Method": "aCompCor",
    "Retained": true,
    "SingularValue": 54.9828082275,
    "VarianceExplained": 0.01060461
  },
  "a_comp_cor_31": {
    "CumulativeVarianceExplained": 0.4317175509,
    "Mask": "combined",
    "Method": "aCompCor",
    "Retained": true,
    "SingularValue": 54.8208520995,
    "VarianceExplained": 0.0105422286
  },
  "a_comp_cor_32": {
    "CumulativeVarianceExplained": 0.4422101901,
    "Mask": "combined",
    "Method": "aCompCor",
    "Retained": true,
    "SingularValue": 54.6917646419,
    "VarianceExplained": 0.0104926392
  },
  "a_comp_cor_33": {
    "CumulativeVarianceExplained": 0.4526231232,
    "Mask": "combined",
    "Method": "aCompCor",
    "Retained": true,
    "SingularValue": 54.4836387523,
    "VarianceExplained": 0.0104129331
  },
  "a_comp_cor_34": {
    "CumulativeVarianceExplained": 0.4629733185,
    "Mask": "combined",
    "Method": "aCompCor",
    "Retained": true,
    "SingularValue": 54.3192593271,
    "VarianceExplained": 0.0103501953
  },
  "a_comp_cor_35": {
    "CumulativeVarianceExplained": 0.4731852843,
    "Mask": "combined",
    "Method": "aCompCor",
    "Retained": true,
    "SingularValue": 53.9553162782,
    "VarianceExplained": 0.0102119658
  },
  "a_comp_cor_36": {
    "CumulativeVarianceExplained": 0.4833328141,
    "Mask": "combined",
    "Method": "aCompCor",
    "Retained": true,
    "SingularValue": 53.7848217286,
    "VarianceExplained": 0.0101475298
  },
  "a_comp_cor_37": {
    "CumulativeVarianceExplained": 0.49342348,
    "Mask": "combined",
    "Method": "aCompCor",
    "Retained": true,
    "SingularValue": 53.6339126262,
    "VarianceExplained": 0.0100906659
  },
  "a_comp_cor_38": {
    "CumulativeVarianceExplained": 0.5034363234,
    "Mask": "combined",
    "Method": "aCompCor",
    "Retained": true,
    "SingularValue": 53.4266911337,
    "VarianceExplained": 0.0100128434
  },
  "aroma_motion_1": {
    "CSFFraction": 0.02,
    "EdgeFraction": 0.53,
    "HighFrequencyContent": 0.06,
    "MaximumRpCorrelation": 0.91,
    "Method": {
      "Name": "ICA-AROMA",
      "Version": "0.4.5"
    },
    "ModelVarianceExplained": 0.1409898008,
    "MotionNoise": true,
    "TotalVarianceExplained": 0.0934372156
  },
  "aroma_motion_10": {
    "CSFFraction": 0.02,
    "EdgeFraction": 0.55,
    "HighFrequencyContent": 0.16,
    "MaximumRpCorrelation": 0.52,
    "Method": {
      "Name": "ICA-AROMA",
      "Version": "0.4.5"
    },
    "ModelVarianceExplained": 0.0521063072,
    "MotionNoise": false,
    "TotalVarianceExplained": 0.03453206
  },
  "aroma_motion_11": {
    "CSFFraction": 0.02,
    "EdgeFraction": 0.66,
    "HighFrequencyContent": 0.08,
    "MaximumRpCorrelation": 0.49,
    "Method": {
      "Name": "ICA-AROMA",
      "Version": "0.4.5"
    },
    "ModelVarianceExplained": 0.0520642692,
    "MotionNoise": true,
    "TotalVarianceExplained": 0.0345042004
  },
  "aroma_motion_12": {
    "CSFFraction": 0.23,
    "EdgeFraction": 0.84,
    "HighFrequencyContent": 0.22,
    "MaximumRpCorrelation": 0.46,
    "Method": {
      "Name": "ICA-AROMA",
      "Version": "0.4.5"
    },
    "ModelVarianceExplained": 0.0514209265,
    "MotionNoise": true,
    "TotalVarianceExplained": 0.0340778423
  },
  "aroma_motion_13": {
    "CSFFraction": 0.08,
    "EdgeFraction": 0.71,
    "HighFrequencyContent": 0.1,
    "MaximumRpCorrelation": 0.39,
    "Method": {
      "Name": "ICA-AROMA",
      "Version": "0.4.5"
    },
    "ModelVarianceExplained": 0.0504547837,
    "MotionNoise": true,
    "TotalVarianceExplained": 0.033437557
  },
  "aroma_motion_14": {
    "CSFFraction": 0.01,
    "EdgeFraction": 0.45,
    "HighFrequencyContent": 0.04,
    "MaximumRpCorrelation": 0.45,
    "Method": {
      "Name": "ICA-AROMA",
      "Version": "0.4.5"
    },
    "ModelVarianceExplained": 0.0468977702,
    "MotionNoise": false,
    "TotalVarianceExplained": 0.0310802416
  },
  "aroma_motion_15": {
    "CSFFraction": 0.04,
    "EdgeFraction": 0.66,
    "HighFrequencyContent": 0.14,
    "MaximumRpCorrelation": 0.66,
    "Method": {
      "Name": "ICA-AROMA",
      "Version": "0.4.5"
    },
    "ModelVarianceExplained": 0.0460586812,
    "MotionNoise": true,
    "TotalVarianceExplained": 0.0305241578
  },
  "aroma_motion_16": {
    "CSFFraction": 0.04,
    "EdgeFraction": 0.66,
    "HighFrequencyContent": 0.12,
    "MaximumRpCorrelation": 0.46,
    "Method": {
      "Name": "ICA-AROMA",
      "Version": "0.4.5"
    },
    "ModelVarianceExplained": 0.0439297814,
    "MotionNoise": true,
    "TotalVarianceExplained": 0.0291132864
  },
  "aroma_motion_17": {
    "CSFFraction": 0.41,
    "EdgeFraction": 0.75,
    "HighFrequencyContent": 0.22,
    "MaximumRpCorrelation": 0.23,
    "Method": {
      "Name": "ICA-AROMA",
      "Version": "0.4.5"
    },
    "ModelVarianceExplained": 0.0414412065,
    "MotionNoise": true,
    "TotalVarianceExplained": 0.0274640501
  },
  "aroma_motion_2": {
    "CSFFraction": 0.25,
    "EdgeFraction": 0.66,
    "HighFrequencyContent": 0.14,
    "MaximumRpCorrelation": 0.44,
    "Method": {
      "Name": "ICA-AROMA",
      "Version": "0.4.5"
    },
    "ModelVarianceExplained": 0.076252834,
    "MotionNoise": true,
    "TotalVarianceExplained": 0.0505345241
  },
  "aroma_motion_3": {
    "CSFFraction": 0.06,
    "EdgeFraction": 0.82,
    "HighFrequencyContent": 0.2,
    "MaximumRpCorrelation": 0.58,
    "Method": {
      "Name": "ICA-AROMA",
      "Version": "0.4.5"
    },
    "ModelVarianceExplained": 0.0618724687,
    "MotionNoise": true,
    "TotalVarianceExplained": 0.0410043221
  },
  "aroma_motion_4": {
    "CSFFraction": 0.3,
    "EdgeFraction": 0.75,
    "HighFrequencyContent": 0.14,
    "MaximumRpCorrelation": 0.57,
    "Method": {
      "Name": "ICA-AROMA",
      "Version": "0.4.5"
    },
    "ModelVarianceExplained": 0.0606664702,
    "MotionNoise": true,
    "TotalVarianceExplained": 0.0402050789
  },
  "aroma_motion_5": {
    "CSFFraction": 0.0,
    "EdgeFraction": 0.52,
    "HighFrequencyContent": 0.14,
    "MaximumRpCorrelation": 0.59,
    "Method": {
      "Name": "ICA-AROMA",
      "Version": "0.4.5"
    },
    "ModelVarianceExplained": 0.0576513985,
    "MotionNoise": false,
    "TotalVarianceExplained": 0.0382069208
  },
  "aroma_motion_6": {
    "CSFFraction": 0.01,
    "EdgeFraction": 0.48,
    "HighFrequencyContent": 0.28,
    "MaximumRpCorrelation": 0.42,
    "Method": {
      "Name": "ICA-AROMA",
      "Version": "0.4.5"
    },
    "ModelVarianceExplained": 0.0566611795,
    "MotionNoise": false,
    "TotalVarianceExplained": 0.0375506797
  },
  "aroma_motion_7": {
    "CSFFraction": 0.11,
    "EdgeFraction": 0.73,
    "HighFrequencyContent": 0.16,
    "MaximumRpCorrelation": 0.41,
    "Method": {
      "Name": "ICA-AROMA",
      "Version": "0.4.5"
    },
    "ModelVarianceExplained": 0.0564578008,
    "MotionNoise": true,
    "TotalVarianceExplained": 0.0374158959
  },
  "aroma_motion_8": {
    "CSFFraction": 0.19,
    "EdgeFraction": 0.6,
    "HighFrequencyContent": 0.14,
    "MaximumRpCorrelation": 0.29,
    "Method": {
      "Name": "ICA-AROMA",
      "Version": "0.4.5"
    },
    "ModelVarianceExplained": 0.0528331496,
    "MotionNoise": true,
    "TotalVarianceExplained": 0.0350137554
  },
  "aroma_motion_9": {
    "CSFFraction": 0.03,
    "EdgeFraction": 0.64,
    "HighFrequencyContent": 0.08,
    "MaximumRpCorrelation": 0.52,
    "Method": {
      "Name": "ICA-AROMA",
      "Version": "0.4.5"
    },
    "ModelVarianceExplained": 0.0522411718,
    "MotionNoise": true,
    "TotalVarianceExplained": 0.0346214379
  },
  "c_comp_cor_00": {
    "CumulativeVarianceExplained": 0.1200308864,
    "Mask": "CSF",
    "Method": "aCompCor",
    "Retained": true,
    "SingularValue": 51.0771114695,
    "VarianceExplained": 0.1200308864
  },
  "c_comp_cor_01": {
    "CumulativeVarianceExplained": 0.2194052474,
    "Mask": "CSF",
    "Method": "aCompCor",
    "Retained": true,
    "SingularValue": 46.4747429866,
    "VarianceExplained": 0.099374361
  },
  "c_comp_cor_02": {
    "CumulativeVarianceExplained": 0.2981975318,
    "Mask": "CSF",
    "Method": "aCompCor",
    "Retained": true,
    "SingularValue": 41.3829711462,
    "VarianceExplained": 0.0787922844
  },
  "c_comp_cor_03": {
    "CumulativeVarianceExplained": 0.3646536204,
    "Mask": "CSF",
    "Method": "aCompCor",
    "Retained": true,
    "SingularValue": 38.0055665178,
    "VarianceExplained": 0.0664560886
  },
  "c_comp_cor_04": {
    "CumulativeVarianceExplained": 0.4010547802,
    "Mask": "CSF",
    "Method": "aCompCor",
    "Retained": true,
    "SingularValue": 28.1279080234,
    "VarianceExplained": 0.0364011599
  },
  "c_comp_cor_05": {
    "CumulativeVarianceExplained": 0.4351679681,
    "Mask": "CSF",
    "Method": "aCompCor",
    "Retained": true,
    "SingularValue": 27.2295820487,
    "VarianceExplained": 0.0341131879
  },
  "c_comp_cor_06": {
    "CumulativeVarianceExplained": 0.4637578261,
    "Mask": "CSF",
    "Method": "aCompCor",
    "Retained": true,
    "SingularValue": 24.927907314,
    "VarianceExplained": 0.028589858
  },
  "c_comp_cor_07": {
    "CumulativeVarianceExplained": 0.4904491072,
    "Mask": "CSF",
    "Method": "aCompCor",
    "Retained": true,
    "SingularValue": 24.0859916661,
    "VarianceExplained": 0.0266912811
  },
  "c_comp_cor_08": {
    "CumulativeVarianceExplained": 0.5156820853,
    "Mask": "CSF",
    "Method": "aCompCor",
    "Retained": true,
    "SingularValue": 23.4187698028,
    "VarianceExplained": 0.0252329781
  },
  "csf": {
    "Method": "Mean"
  },
  "csf_wm": {
    "Method": "Mean"
  },
  "global_signal": {
    "Method": "Mean"
  },
  "t_comp_cor_00": {
    "CumulativeVarianceExplained": 0.241383139,
    "Method": "tCompCor",
    "Retained": true,
    "SingularValue": 175.7721106297,
    "VarianceExplained": 0.241383139
  },
  "t_comp_cor_01": {
    "CumulativeVarianceExplained": 0.4344079971,
    "Method": "tCompCor",
    "Retained": true,
    "SingularValue": 157.182113227,
    "VarianceExplained": 0.1930248581
  },
  "t_comp_cor_02": {
    "CumulativeVarianceExplained": 0.4830351463,
    "Method": "tCompCor",
    "Retained": true,
    "SingularValue": 78.8925341928,
    "VarianceExplained": 0.0486271491
  },
  "t_comp_cor_03": {
    "CumulativeVarianceExplained": 0.5243338183,
    "Method": "tCompCor",
    "Retained": true,
    "SingularValue": 72.705044726,
    "VarianceExplained": 0.041298672
  },
  "tcompcor": {
    "Method": "Mean"
  },
  "w_comp_cor_00": {
    "CumulativeVarianceExplained": 0.0182410305,
    "Mask": "WM",
    "Method": "aCompCor",
    "Retained": true,
    "SingularValue": 64.1560388839,
    "VarianceExplained": 0.0182410305
  },
  "w_comp_cor_01": {
    "CumulativeVarianceExplained": 0.0361497572,
    "Mask": "WM",
    "Method": "aCompCor",
    "Retained": true,
    "SingularValue": 63.568975414,
    "VarianceExplained": 0.0179087267
  },
  "w_comp_cor_02": {
    "CumulativeVarianceExplained": 0.052191629,
    "Mask": "WM",
    "Method": "aCompCor",
    "Retained": true,
    "SingularValue": 60.1645091303,
    "VarianceExplained": 0.0160418718
  },
  "w_comp_cor_03": {
    "CumulativeVarianceExplained": 0.0673043737,
    "Mask": "WM",
    "Method": "aCompCor",
    "Retained": true,
    "SingularValue": 58.3961923984,
    "VarianceExplained": 0.0151127447
  },
  "w_comp_cor_04": {
    "CumulativeVarianceExplained": 0.0821237501,
    "Mask": "WM",
    "Method": "aCompCor",
    "Retained": true,
    "SingularValue": 57.8266217852,
    "VarianceExplained": 0.0148193764
  },
  "w_comp_cor_05": {
    "CumulativeVarianceExplained": 0.0966232474,
    "Mask": "WM",
    "Method": "aCompCor",
    "Retained": true,
    "SingularValue": 57.1991177051,
    "VarianceExplained": 0.0144994973
  },
  "w_comp_cor_06": {
    "CumulativeVarianceExplained": 0.1107630736,
    "Mask": "WM",
    "Method": "aCompCor",
    "Retained": true,
    "SingularValue": 56.4852289342,
    "VarianceExplained": 0.0141398262
  },
  "w_comp_cor_07": {
    "CumulativeVarianceExplained": 0.1245707945,
    "Mask": "WM",
    "Method": "aCompCor",
    "Retained": true,
    "SingularValue": 55.8179467019,
    "VarianceExplained": 0.0138077209
  },
  "w_comp_cor_08": {
    "CumulativeVarianceExplained": 0.1381550506,
    "Mask": "WM",
    "Method": "aCompCor",
    "Retained": true,
    "SingularValue": 55.3644242928,
    "VarianceExplained": 0.0135842561
  },
  "w_comp_cor_09": {
    "CumulativeVarianceExplained": 0.1514262397,
    "Mask": "WM",
    "Method": "aCompCor",
    "Retained": true,
    "SingularValue": 54.7227324692,
    "VarianceExplained": 0.013271189
  },
  "w_comp_cor_10": {
    "CumulativeVarianceExplained": 0.1645605194,
    "Mask": "WM",
    "Method": "aCompCor",
    "Retained": true,
    "SingularValue": 54.4397331873,
    "VarianceExplained": 0.0131342797
  },
  "w_comp_cor_11": {
    "CumulativeVarianceExplained": 0.1775757986,
    "Mask": "WM",
    "Method": "aCompCor",
    "Retained": true,
    "SingularValue": 54.1925519176,
    "VarianceExplained": 0.0130152792
  },
  "w_comp_cor_12": {
    "CumulativeVarianceExplained": 0.1904945196,
    "Mask": "WM",
    "Method": "aCompCor",
    "Retained": true,
    "SingularValue": 53.9911548289,
    "VarianceExplained": 0.012918721
  },
  "w_comp_cor_13": {
    "CumulativeVarianceExplained": 0.2033126257,
    "Mask": "WM",
    "Method": "aCompCor",
    "Retained": true,
    "SingularValue": 53.7804940667,
    "VarianceExplained": 0.0128181061
  },
  "w_comp_cor_14": {
    "CumulativeVarianceExplained": 0.2160242991,
    "Mask": "WM",
    "Method": "aCompCor",
    "Retained": true,
    "SingularValue": 53.556750683,
    "VarianceExplained": 0.0127116734
  },
  "w_comp_cor_15": {
    "CumulativeVarianceExplained": 0.2286998801,
    "Mask": "WM",
    "Method": "aCompCor",
    "Retained": true,
    "SingularValue": 53.480664464,
    "VarianceExplained": 0.012675581
  },
  "w_comp_cor_16": {
    "CumulativeVarianceExplained": 0.2411694728,
    "Mask": "WM",
    "Method": "aCompCor",
    "Retained": true,
    "SingularValue": 53.0443329744,
    "VarianceExplained": 0.0124695928
  },
  "w_comp_cor_17": {
    "CumulativeVarianceExplained": 0.2535685729,
    "Mask": "WM",
    "Method": "aCompCor",
    "Retained": true,
    "SingularValue": 52.894186263,
    "VarianceExplained": 0.0123991001
  },
  "w_comp_cor_18": {
    "CumulativeVarianceExplained": 0.2658674216,
    "Mask": "WM",
    "Method": "aCompCor",
    "Retained": true,
    "SingularValue": 52.6799174972,
    "VarianceExplained": 0.0122988487
  },
  "w_comp_cor_19": {
    "CumulativeVarianceExplained": 0.2780213947,
    "Mask": "WM",
    "Method": "aCompCor",
    "Retained": true,
    "SingularValue": 52.3687240783,
    "VarianceExplained": 0.0121539731
  },
  "w_comp_cor_20": {
    "CumulativeVarianceExplained": 0.2900521424,
    "Mask": "WM",
    "Method": "aCompCor",
    "Retained": true,
    "SingularValue": 52.1025725735,
    "VarianceExplained": 0.0120307477
  },
  "w_comp_cor_21": {
    "CumulativeVarianceExplained": 0.3019159648,
    "Mask": "WM",
    "Method": "aCompCor",
    "Retained": true,
    "SingularValue": 51.7398511417,
    "VarianceExplained": 0.0118638224
  },
  "w_comp_cor_22": {
    "CumulativeVarianceExplained": 0.3136844774,
    "Mask": "WM",
    "Method": "aCompCor",
    "Retained": true,
    "SingularValue": 51.5316023532,
    "VarianceExplained": 0.0117685127
  },
  "w_comp_cor_23": {
    "CumulativeVarianceExplained": 0.3254030647,
    "Mask": "WM",
    "Method": "aCompCor",
    "Retained": true,
    "SingularValue": 51.4221803278,
    "VarianceExplained": 0.0117185873
  },
  "w_comp_cor_24": {
    "CumulativeVarianceExplained": 0.3370427943,
    "Mask": "WM",
    "Method": "aCompCor",
    "Retained": true,
    "SingularValue": 51.2488709419,
    "VarianceExplained": 0.0116397295
  },
  "w_comp_cor_25": {
    "CumulativeVarianceExplained": 0.3486456991,
    "Mask": "WM",
    "Method": "aCompCor",
    "Retained": true,
    "SingularValue": 51.1677383908,
    "VarianceExplained": 0.0116029048
  },
  "w_comp_cor_26": {
    "CumulativeVarianceExplained": 0.3601339076,
    "Mask": "WM",
    "Method": "aCompCor",
    "Retained": true,
    "SingularValue": 50.9142102478,
    "VarianceExplained": 0.0114882085
  },
  "w_comp_cor_27": {
    "CumulativeVarianceExplained": 0.3715256799,
    "Mask": "WM",
    "Method": "aCompCor",
    "Retained": true,
    "SingularValue": 50.700063796,
    "VarianceExplained": 0.0113917723
  },
  "w_comp_cor_28": {
    "CumulativeVarianceExplained": 0.3827668221,
    "Mask": "WM",
    "Method": "aCompCor",
    "Retained": true,
    "SingularValue": 50.3637522106,
    "VarianceExplained": 0.0112411422
  },
  "w_comp_cor_29": {
    "CumulativeVarianceExplained": 0.3939577304,
    "Mask": "WM",
    "Method": "aCompCor",
    "Retained": true,
    "SingularValue": 50.2510945042,
    "VarianceExplained": 0.0111909083
  },
  "w_comp_cor_30": {
    "CumulativeVarianceExplained": 0.4050327168,
    "Mask": "WM",
    "Method": "aCompCor",
    "Retained": true,
    "SingularValue": 49.9901520772,
    "VarianceExplained": 0.0110749864
  },
  "w_comp_cor_31": {
    "CumulativeVarianceExplained": 0.4160483425,
    "Mask": "WM",
    "Method": "aCompCor",
    "Retained": true,
    "SingularValue": 49.8560013386,
    "VarianceExplained": 0.0110156257
  },
  "w_comp_cor_32": {
    "CumulativeVarianceExplained": 0.4270179927,
    "Mask": "WM",
    "Method": "aCompCor",
    "Retained": true,
    "SingularValue": 49.7518513465,
    "VarianceExplained": 0.0109696502
  },
  "w_comp_cor_33": {
    "CumulativeVarianceExplained": 0.4379272279,
    "Mask": "WM",
    "Method": "aCompCor",
    "Retained": true,
    "SingularValue": 49.6146589469,
    "VarianceExplained": 0.0109092352
  },
  "w_comp_cor_34": {
    "CumulativeVarianceExplained": 0.448795683,
    "Mask": "WM",
    "Method": "aCompCor",
    "Retained": true,
    "SingularValue": 49.5218389941,
    "VarianceExplained": 0.010868455
  },
  "w_comp_cor_35": {
    "CumulativeVarianceExplained": 0.4595631602,
    "Mask": "WM",
    "Method": "aCompCor",
    "Retained": true,
    "SingularValue": 49.2912507336,
    "VarianceExplained": 0.0107674772
  },
  "w_comp_cor_36": {
    "CumulativeVarianceExplained": 0.470211339,
    "Mask": "WM",
    "Method": "aCompCor",
    "Retained": true,
    "SingularValue": 49.017428588,
    "VarianceExplained": 0.0106481788
  },
  "w_comp_cor_37": {
    "CumulativeVarianceExplained": 0.480812711,
    "Mask": "WM",
    "Method": "aCompCor",
    "Retained": true,
    "SingularValue": 48.909575688,
    "VarianceExplained": 0.010601372
  },
  "w_comp_cor_38": {
    "CumulativeVarianceExplained": 0.4913053877,
    "Mask": "WM",
    "Method": "aCompCor",
    "Retained": true,
    "SingularValue": 48.658195904,
    "VarianceExplained": 0.0104926767
  },
  "w_comp_cor_39": {
    "CumulativeVarianceExplained": 0.5017369895,
    "Mask": "WM",
    "Method": "aCompCor",
    "Retained": true,
    "SingularValue": 48.5163765309,
    "VarianceExplained": 0.0104316018
  },
  "white_matter": {
    "Method": "Mean"
  }
}