{
  "a_comp_cor_00": {
    "CumulativeVarianceExplained": 0.0270739593,
    "Mask": "combined",
    "Method": "aCompCor",
    "Retained": true,
    "SingularValue": 87.2032012355,
    "VarianceExplained": 0.0270739593
  },
  "a_comp_cor_01": {
    "CumulativeVarianceExplained": 0.0482191387,
    "Mask": "combined",
    "Method": "aCompCor",
    "Retained": true,
    "SingularValue": 77.0658957424,
    "VarianceExplained": 0.0211451795
  },
  "a_comp_cor_02": {
    "CumulativeVarianceExplained": 0.0682949107,
    "Mask": "combined",
    "Method": "aCompCor",
    "Retained": true,
    "SingularValue": 75.0918268449,
    "VarianceExplained": 0.020075772
  },
  "a_comp_cor_03": {
    "CumulativeVarianceExplained": 0.0870555083,
    "Mask": "combined",
    "Method": "aCompCor",
    "Retained": true,
    "SingularValue": 72.5905148089,
    "VarianceExplained": 0.0187605976
  },
  "a_comp_cor_04": {
    "CumulativeVarianceExplained": 0.1039465255,
    "Mask": "combined",
    "Method": "aCompCor",
    "Retained": true,
    "SingularValue": 68.8786211765,
    "VarianceExplained": 0.0168910172
  },
  "a_comp_cor_05": {
    "CumulativeVarianceExplained": 0.1202201674,
    "Mask": "combined",
    "Method": "aCompCor",
    "Retained": true,
    "SingularValue": 67.6081294071,
    "VarianceExplained": 0.0162736419
  },
  "a_comp_cor_06": {
    "CumulativeVarianceExplained": 0.1353456005,
    "Mask": "combined",
    "Method": "aCompCor",
    "Retained": true,
    "SingularValue": 65.1794141348,
    "VarianceExplained": 0.0151254331
  },
  "a_comp_cor_07": {
    "CumulativeVarianceExplained": 0.1495948236,
    "Mask": "combined",
    "Method": "aCompCor",
    "Retained": true,
    "SingularValue": 63.2633428658,
    "VarianceExplained": 0.0142492231
  },
  "a_comp_cor_08": {
    "CumulativeVarianceExplained": 0.1628902872,
    "Mask": "combined",
    "Method": "aCompCor",
    "Retained": true,
    "SingularValue": 61.1094373024,
    "VarianceExplained": 0.0132954636
  },
  "a_comp_cor_09": {
    "CumulativeVarianceExplained": 0.1760878295,
    "Mask": "combined",
    "Method": "aCompCor",
    "Retained": true,
    "SingularValue": 60.8839854627,
    "VarianceExplained": 0.0131975423
  },
  "a_comp_cor_10": {
    "CumulativeVarianceExplained": 0.1889771574,
    "Mask": "combined",
    "Method": "aCompCor",
    "Retained": true,
    "SingularValue": 60.1688455441,
    "VarianceExplained": 0.0128893279
  },
  "a_comp_cor_11": {
    "CumulativeVarianceExplained": 0.201811312,
    "Mask": "combined",
    "Method": "aCompCor",
    "Retained": true,
    "SingularValue": 60.0399299183,
    "VarianceExplained": 0.0128341546
  },
  "a_comp_cor_12": {
    "CumulativeVarianceExplained": 0.2143065774,
    "Mask": "combined",
    "Method": "aCompCor",
    "Retained": true,
    "SingularValue": 59.2419417636,
    "VarianceExplained": 0.0124952654
  },
  "a_comp_cor_13": {
    "CumulativeVarianceExplained": 0.2267244619,
    "Mask": "combined",
    "Method": "aCompCor",
    "Retained": true,
    "SingularValue": 59.0582198122,
    "VarianceExplained": 0.0124178846
  },
  "a_comp_cor_14": {
    "CumulativeVarianceExplained": 0.2390159993,
    "Mask": "combined",
    "Method": "aCompCor",
    "Retained": true,
    "SingularValue": 58.7570044112,
    "VarianceExplained": 0.0122915374
  },
  "a_comp_cor_15": {
    "CumulativeVarianceExplained": 0.2511750925,
    "Mask": "combined",
    "Method": "aCompCor",
    "Retained": true,
    "SingularValue": 58.4395866517,
    "VarianceExplained": 0.0121590931
  },
  "a_comp_cor_16": {
    "CumulativeVarianceExplained": 0.2632208738,
    "Mask": "combined",
    "Method": "aCompCor",
    "Retained": true,
    "SingularValue": 58.1666469892,
    "VarianceExplained": 0.0120457813
  },
  "a_comp_cor_17": {
    "CumulativeVarianceExplained": 0.2750125874,
    "Mask": "combined",
    "Method": "aCompCor",
    "Retained": true,
    "SingularValue": 57.5499570037,
    "VarianceExplained": 0.0117917136
  },
  "a_comp_cor_18": {
    "CumulativeVarianceExplained": 0.2867446447,
    "Mask": "combined",
    "Method": "aCompCor",
    "Retained": true,
    "SingularValue": 57.4041948856,
    "VarianceExplained": 0.0117320573
  },
  "a_comp_cor_19": {
    "CumulativeVarianceExplained": 0.2983969943,
    "Mask": "combined",
    "Method": "aCompCor",
    "Retained": true,
    "SingularValue": 57.2088602614,
    "VarianceExplained": 0.0116523496
  },
  "a_comp_cor_20": {
    "CumulativeVarianceExplained": 0.3099465501,
    "Mask": "combined",
    "Method": "aCompCor",
    "Retained": true,
    "SingularValue": 56.9559611677,
    "VarianceExplained": 0.0115495559
  },
  "a_comp_cor_21": {
    "CumulativeVarianceExplained": 0.3213382262,
    "Mask": "combined",
    "Method": "aCompCor",
    "Retained": true,
    "SingularValue": 56.5653338793,
    "VarianceExplained": 0.011391676
  },
  "a_comp_cor_22": {
    "CumulativeVarianceExplained": 0.3326160312,
    "Mask": "combined",
    "Method": "aCompCor",
    "Retained": true,
    "SingularValue": 56.2819108896,
    "VarianceExplained": 0.011277805
  },
  "a_comp_cor_23": {
    "CumulativeVarianceExplained": 0.3438503579,
    "Mask": "combined",
    "Method": "aCompCor",
    "Retained": true,
    "SingularValue": 56.1733166805,
    "VarianceExplained": 0.0112343267
  },
  "a_comp_cor_24": {
    "CumulativeVarianceExplained": 0.3548984939,
    "Mask": "combined",
    "Method": "aCompCor",
    "Retained": true,
    "SingularValue": 55.7058811978,
    "VarianceExplained": 0.011048136
  },
  "a_comp_cor_25": {
    "CumulativeVarianceExplained": 0.3658998273,
    "Mask": "combined",
    "Method": "aCompCor",
    "Retained": true,
    "SingularValue": 55.5877640475,
    "VarianceExplained": 0.0110013334
  },
  "a_comp_cor_26": {
    "CumulativeVarianceExplained": 0.3768718917,
    "Mask": "combined",
    "Method": "aCompCor",
    "Retained": true,
    "SingularValue": 55.5137694015,
    "VarianceExplained": 0.0109720644
  },
  "a_comp_cor_27": {
    "CumulativeVarianceExplained": 0.3876632334,
    "Mask": "combined",
    "Method": "aCompCor",
    "Retained": true,
    "SingularValue": 55.0546828508,
    "VarianceExplained": 0.0107913417
  },
  "a_comp_cor_28": {
    "CumulativeVarianceExplained": 0.3984413507,
    "Mask": "combined",
    "Method": "aCompCor",
    "Retained": true,
    "SingularValue": 55.0209387927,
    "VarianceExplained": 0.0107781173
  },
  "a_comp_cor_29": {
    "CumulativeVarianceExplained": 0.4091176181,
    "Mask": "combined",
    "Method": "aCompCor",
    "Retained": true,
    "SingularValue": 54.760355972,
    "VarianceExplained": 0.0106762673
  },
  "a_comp_cor_30": {
    "CumulativeVarianceExplained": 0.4197391701,
    "Mask": "combined",
    "Method": "aCompCor",
    "Retained": true,
    "SingularValue": 54.6198538471,
    "VarianceExplained": 0.0106215521
  },
  "a_comp_cor_31": {
    "CumulativeVarianceExplained": 0.4302604214,
    "Mask": "combined",
    "Method": "aCompCor",
    "Retained": true,
    "SingularValue": 54.3613507604,
    "VarianceExplained": 0.0105212513
  },
  "a_comp_cor_32": {
    "CumulativeVarianceExplained": 0.4407192937,
    "Mask": "combined",
    "Method": "aCompCor",
    "Retained": true,
    "SingularValue": 54.1999608218,
    "VarianceExplained": 0.0104588723
  },
  "a_comp_cor_33": {
    "CumulativeVarianceExplained": 0.4510989458,
    "Mask": "combined",
    "Method": "aCompCor",
    "Retained": true,
    "SingularValue": 53.9943032169,
    "VarianceExplained": 0.0103796521
  },
  "a_comp_cor_34": {
    "CumulativeVarianceExplained": 0.4614212605,
    "Mask": "combined",
    "Method": "aCompCor",
    "Retained": true,
    "SingularValue": 53.8449639441,
    "VarianceExplained": 0.0103223147
  },
  "a_comp_cor_35": {
    "CumulativeVarianceExplained": 0.4715863137,
    "Mask": "combined",
    "Method": "aCompCor",
    "Retained": true,
    "SingularValue": 53.4332231289,
    "VarianceExplained": 0.0101650533
  },
  "a_comp_cor_36": {
    "CumulativeVarianceExplained": 0.4816830074,
    "Mask": "combined",
    "Method": "aCompCor",
    "Retained": true,
    "SingularValue": 53.2532518789,
    "VarianceExplained": 0.0100966937
  },
  "a_comp_cor_37": {
    "CumulativeVarianceExplained": 0.4916863807,
    "Mask": "combined",
    "Method": "aCompCor",
    "Retained": true,
    "SingularValue": 53.0065795453,
    "VarianceExplained": 0.0100033733
  },
  "a_comp_cor_38": {
    "CumulativeVarianceExplained": 0.5016107391,
    "Mask": "combined",
    "Method": "aCompCor",
    "Retained": true,
    "SingularValue": 52.7968197465,
    "VarianceExplained": 0.0099243584
  },
  "aroma_motion_1": {
    "CSFFraction": 0.02,
    "EdgeFraction": 0.6,
    "HighFrequencyContent": 0.06,
    "MaximumRpCorrelation": 0.96,
    "Method": {
      "Name": "ICA-AROMA",
      "Version": "0.4.5"
    },
    "ModelVarianceExplained": 0.132725939,
    "MotionNoise": true,
    "TotalVarianceExplained": 0.1061001054
  },
  "aroma_motion_10": {
    "CSFFraction": 0.04,
    "EdgeFraction": 0.69,
    "HighFrequencyContent": 0.18,
    "MaximumRpCorrelation": 0.56,
    "Method": {
      "Name": "ICA-AROMA",
      "Version": "0.4.5"
    },
    "ModelVarianceExplained": 0.0415542897,
    "MotionNoise": true,
    "TotalVarianceExplained": 0.0332181829
  },
  "aroma_motion_11": {
    "CSFFraction": 0.07,
    "EdgeFraction": 0.77,
    "HighFrequencyContent": 0.22,
    "MaximumRpCorrelation": 0.49,
    "Method": {
      "Name": "ICA-AROMA",
      "Version": "0.4.5"
    },
    "ModelVarianceExplained": 0.0399811473,
    "MotionNoise": true,
    "TotalVarianceExplained": 0.0319606249
  },
  "aroma_motion_12": {
    "CSFFraction": 0.19,
    "EdgeFraction": 0.61,
    "HighFrequencyContent": 0.42,
    "MaximumRpCorrelation": 0.62,
    "Method": {
      "Name": "ICA-AROMA",
      "Version": "0.4.5"
    },
    "ModelVarianceExplained": 0.0394480575,
    "MotionNoise": true,
    "TotalVarianceExplained": 0.0315344769
  },
  "aroma_motion_13": {
    "CSFFraction": 0.01,
    "EdgeFraction": 0.58,
    "HighFrequencyContent": 0.08,
    "MaximumRpCorrelation": 0.22,
    "Method": {
      "Name": "ICA-AROMA",
      "Version": "0.4.5"
    },
    "ModelVarianceExplained": 0.0393672487,
    "MotionNoise": false,
    "TotalVarianceExplained": 0.031469879
  },
  "aroma_motion_14": {
    "CSFFraction": 0.02,
    "EdgeFraction": 0.46,
    "HighFrequencyContent": 0.08,
    "MaximumRpCorrelation": 0.59,
    "Method": {
      "Name": "ICA-AROMA",
      "Version": "0.4.5"
    },
    "ModelVarianceExplained": 0.0387274744,
    "MotionNoise": false,
    "TotalVarianceExplained": 0.0309584483
  },
  "aroma_motion_15": {
    "CSFFraction": 0.24,
    "EdgeFraction": 0.71,
    "HighFrequencyContent": 0.6,
    "MaximumRpCorrelation": 0.56,
    "Method": {
      "Name": "ICA-AROMA",
      "Version": "0.4.5"
    },
    "ModelVarianceExplained": 0.037549187,
    "MotionNoise": true,
    "TotalVarianceExplained": 0.0300165343
  },
  "aroma_motion_16": {
    "CSFFraction": 0.01,
    "EdgeFraction": 0.51,
    "HighFrequencyContent": 0.08,
    "MaximumRpCorrelation": 0.39,
    "Method": {
      "Name": "ICA-AROMA",
      "Version": "0.4.5"
    },
    "ModelVarianceExplained": 0.0370957114,
    "MotionNoise": false,
    "TotalVarianceExplained": 0.0296540293
  },
  "aroma_motion_17": {
    "CSFFraction": 0.02,
    "EdgeFraction": 0.67,
    "HighFrequencyContent": 0.12,
    "MaximumRpCorrelation": 0.55,
    "Method": {
      "Name": "ICA-AROMA",
      "Version": "0.4.5"
    },
    "ModelVarianceExplained": 0.0342922932,
    "MotionNoise": true,
    "TotalVarianceExplained": 0.0274129982
  },
  "aroma_motion_18": {
    "CSFFraction": 0.01,
    "EdgeFraction": 0.71,
    "HighFrequencyContent": 0.2,
    "MaximumRpCorrelation": 0.63,
    "Method": {
      "Name": "ICA-AROMA",
      "Version": "0.4.5"
    },
    "ModelVarianceExplained": 0.0318514395,
    "MotionNoise": true,
    "TotalVarianceExplained": 0.0254617983
  },
  "aroma_motion_19": {
    "CSFFraction": 0.1,
    "EdgeFraction": 0.78,
    "HighFrequencyContent": 0.42,
    "MaximumRpCorrelation": 0.53,
    "Method": {
      "Name": "ICA-AROMA",
      "Version": "0.4.5"
    },
    "ModelVarianceExplained": 0.0295060225,
    "MotionNoise": true,
    "TotalVarianceExplained": 0.0235868898
  },
  "aroma_motion_2": {
    "CSFFraction": 0.03,
    "EdgeFraction": 0.58,
    "HighFrequencyContent": 0.08,
    "MaximumRpCorrelation": 0.9,
    "Method": {
      "Name": "ICA-AROMA",
      "Version": "0.4.5"
    },
    "ModelVarianceExplained": 0.0786970661,
    "MotionNoise": true,
    "TotalVarianceExplained": 0.0629098356
  },
  "aroma_motion_20": {
    "CSFFraction": 0.3,
    "EdgeFraction": 0.78,
    "HighFrequencyContent": 0.62,
    "MaximumRpCorrelation": 0.41,
    "Method": {
      "Name": "ICA-AROMA",
      "Version": "0.4.5"
    },
    "ModelVarianceExplained": 0.0289050367,
    "MotionNoise": true,
    "TotalVarianceExplained": 0.0231064663
  },
  "aroma_motion_21": {
    "CSFFraction": 0.09,
    "EdgeFraction": 0.7,
    "HighFrequencyContent": 0.44,
    "MaximumRpCorrelation": 0.34,
    "Method": {
      "Name": "ICA-AROMA",
      "Version": "0.4.5"
    },
    "ModelVarianceExplained": 0.0280487944,
    "MotionNoise": true,
    "TotalVarianceExplained": 0.0224219927
  },
  "aroma_motion_3": {
    "CSFFraction": 0.03,
    "EdgeFraction": 0.64,
    "HighFrequencyContent": 0.08,
    "MaximumRpCorrelation": 0.89,
    "Method": {
      "Name": "ICA-AROMA",
      "Version": "0.4.5"
    },
    "ModelVarianceExplained": 0.0661269345,
    "MotionNoise": true,
    "TotalVarianceExplained": 0.0528613681
  },
  "aroma_motion_4": {
    "CSFFraction": 0.01,
    "EdgeFraction": 0.5,
    "HighFrequencyContent": 0.16,
    "MaximumRpCorrelation": 0.38,
    "Method": {
      "Name": "ICA-AROMA",
      "Version": "0.4.5"
    },
    "ModelVarianceExplained": 0.056334909,
    "MotionNoise": false,
    "TotalVarianceExplained": 0.0450336974
  },
  "aroma_motion_5": {
    "CSFFraction": 0.16,
    "EdgeFraction": 0.63,
    "HighFrequencyContent": 0.22,
    "MaximumRpCorrelation": 0.75,
    "Method": {
      "Name": "ICA-AROMA",
      "Version": "0.4.5"
    },
    "ModelVarianceExplained": 0.0534857627,
    "MotionNoise": true,
    "TotalVarianceExplained": 0.0427561116
  },
  "aroma_motion_6": {
    "CSFFraction": 0.02,
    "EdgeFraction": 0.54,
    "HighFrequencyContent": 0.1,
    "MaximumRpCorrelation": 0.82,
    "Method": {
      "Name": "ICA-AROMA",
      "Version": "0.4.5"
    },
    "ModelVarianceExplained": 0.0490257748,
    "MotionNoise": true,
    "TotalVarianceExplained": 0.0391908312
  },
  "aroma_motion_7": {
    "CSFFraction": 0.0,
    "EdgeFraction": 0.4,
    "HighFrequencyContent": 0.14,
    "MaximumRpCorrelation": 0.4,
    "Method": {
      "Name": "ICA-AROMA",
      "Version": "0.4.5"
    },
    "ModelVarianceExplained": 0.0479994775,
    "MotionNoise": false,
    "TotalVarianceExplained": 0.0383704169
  },
  "aroma_motion_8": {
    "CSFFraction": 0.13,
    "EdgeFraction": 0.74,
    "HighFrequencyContent": 0.42,
    "MaximumRpCorrelation": 0.77,
    "Method": {
      "Name": "ICA-AROMA",
      "Version": "0.4.5"
    },
    "ModelVarianceExplained": 0.0468910164,
    "MotionNoise": true,
    "TotalVarianceExplained": 0.0374843216
  },
  "aroma_motion_9": {
    "CSFFraction": 0.01,
    "EdgeFraction": 0.42,
    "HighFrequencyContent": 0.08,
    "MaximumRpCorrelation": 0.38,
    "Method": {
      "Name": "ICA-AROMA",
      "Version": "0.4.5"
    },
    "ModelVarianceExplained": 0.0423864178,
    "MotionNoise": false,
    "TotalVarianceExplained": 0.0338833798
  },
  "c_comp_cor_00": {
    "CumulativeVarianceExplained": 0.0962591364,
    "Mask": "CSF",
    "Method": "aCompCor",
    "Retained": true,
    "SingularValue": 48.1097800301,
    "VarianceExplained": 0.0962591364
  },
  "c_comp_cor_01": {
    "CumulativeVarianceExplained": 0.1633940729,
    "Mask": "CSF",
    "Method": "aCompCor",
    "Retained": true,
    "SingularValue": 40.1778489701,
    "VarianceExplained": 0.0671349365
  },
  "c_comp_cor_02": {
    "CumulativeVarianceExplained": 0.2283704831,
    "Mask": "CSF",
    "Method": "aCompCor",
    "Retained": true,
    "SingularValue": 39.5266718016,
    "VarianceExplained": 0.0649764102
  },
  "c_comp_cor_03": {
    "CumulativeVarianceExplained": 0.2825041798,
    "Mask": "CSF",
    "Method": "aCompCor",
    "Retained": true,
    "SingularValue": 36.0783139549,
    "VarianceExplained": 0.0541336967
  },
  "c_comp_cor_04": {
    "CumulativeVarianceExplained": 0.331719956,
    "Mask": "CSF",
    "Method": "aCompCor",
    "Retained": true,
    "SingularValue": 34.4004845528,
    "VarianceExplained": 0.0492157761
  },
  "c_comp_cor_05": {
    "CumulativeVarianceExplained": 0.3714951462,
    "Mask": "CSF",
    "Method": "aCompCor",
    "Retained": true,
    "SingularValue": 30.9256277103,
    "VarianceExplained": 0.0397751902
  },
  "c_comp_cor_06": {
    "CumulativeVarianceExplained": 0.4045886381,
    "Mask": "CSF",
    "Method": "aCompCor",
    "Retained": true,
    "SingularValue": 28.2087400193,
    "VarianceExplained": 0.0330934919
  },
  "c_comp_cor_07": {
    "CumulativeVarianceExplained": 0.434200802,
    "Mask": "CSF",
    "Method": "aCompCor",
    "Retained": true,
    "SingularValue": 26.6837868137,
    "VarianceExplained": 0.0296121638
  },
  "c_comp_cor_08": {
    "CumulativeVarianceExplained": 0.4614461983,
    "Mask": "CSF",
    "Method": "aCompCor",
    "Retained": true,
    "SingularValue": 25.5952252256,
    "VarianceExplained": 0.0272453963
  },
  "c_comp_cor_09": {
    "CumulativeVarianceExplained": 0.4846236226,
    "Mask": "CSF",
    "Method": "aCompCor",
    "Retained": true,
    "SingularValue": 23.6072270098,
    "VarianceExplained": 0.0231774243
  },
  "c_comp_cor_10": {
    "CumulativeVarianceExplained": 0.5066226907,
    "Mask": "CSF",
    "Method": "aCompCor",
    "Retained": true,
    "SingularValue": 22.9992955169,
    "VarianceExplained": 0.0219990682
  },
  "csf": {
    "Method": "Mean"
  },
  "csf_wm": {
    "Method": "Mean"
  },
  "global_signal": {
    "Method": "Mean"
  },
  "t_comp_cor_00": {
    "CumulativeVarianceExplained": 0.1513697746,
    "Method": "tCompCor",
    "Retained": true,
    "SingularValue": 140.9513494457,
    "VarianceExplained": 0.1513697746
  },
  "t_comp_cor_01": {
    "CumulativeVarianceExplained": 0.2557518918,
    "Method": "tCompCor",
    "Retained": true,
    "SingularValue": 117.04765221,
    "VarianceExplained": 0.1043821172
  },
  "t_comp_cor_02": {
    "CumulativeVarianceExplained": 0.3523730082,
    "Method": "tCompCor",
    "Retained": true,
    "SingularValue": 112.6122618935,
    "VarianceExplained": 0.0966211164
  },
  "t_comp_cor_03": {
    "CumulativeVarianceExplained": 0.410579285,
    "Method": "tCompCor",
    "Retained": true,
    "SingularValue": 87.4046556154,
    "VarianceExplained": 0.0582062767
  },
  "t_comp_cor_04": {
    "CumulativeVarianceExplained": 0.4597712436,
    "Method": "tCompCor",
    "Retained": true,
    "SingularValue": 80.3520041826,
    "VarianceExplained": 0.0491919587
  },
  "t_comp_cor_05": {
    "CumulativeVarianceExplained": 0.5007254487,
    "Method": "tCompCor",
    "Retained": true,
    "SingularValue": 73.3160242831,
    "VarianceExplained": 0.0409542051
  },
  "tcompcor": {
    "Method": "Mean"
  },
  "w_comp_cor_00": {
    "CumulativeVarianceExplained": 0.0202838827,
    "Mask": "WM",
    "Method": "aCompCor",
    "Retained": true,
    "SingularValue": 67.0365139794,
    "VarianceExplained": 0.0202838827
  },
  "w_comp_cor_01": {
    "CumulativeVarianceExplained": 0.0370591041,
    "Mask": "WM",
    "Method": "aCompCor",
    "Retained": true,
    "SingularValue": 60.9635161723,
    "VarianceExplained": 0.0167752214
  },
  "w_comp_cor_02": {
    "CumulativeVarianceExplained": 0.0536625666,
    "Mask": "WM",
    "Method": "aCompCor",
    "Retained": true,
    "SingularValue": 60.650615095,
    "VarianceExplained": 0.0166034625
  },
  "w_comp_cor_03": {
    "CumulativeVarianceExplained": 0.0690662764,
    "Mask": "WM",
    "Method": "aCompCor",
    "Retained": true,
    "SingularValue": 58.418249927,
    "VarianceExplained": 0.0154037099
  },
  "w_comp_cor_04": {
    "CumulativeVarianceExplained": 0.0840217679,
    "Mask": "WM",
    "Method": "aCompCor",
    "Retained": true,
    "SingularValue": 57.562045915,
    "VarianceExplained": 0.0149554914
  },
  "w_comp_cor_05": {
    "CumulativeVarianceExplained": 0.0987937387,
    "Mask": "WM",
    "Method": "aCompCor",
    "Retained": true,
    "SingularValue": 57.2077803043,
    "VarianceExplained": 0.0147719708
  },
  "w_comp_cor_06": {
    "CumulativeVarianceExplained": 0.1131317548,
    "Mask": "WM",
    "Method": "aCompCor",
    "Retained": true,
    "SingularValue": 56.3612231566,
    "VarianceExplained": 0.0143380161
  },
  "w_comp_cor_07": {
    "CumulativeVarianceExplained": 0.1267579734,
    "Mask": "WM",
    "Method": "aCompCor",
    "Retained": true,
    "SingularValue": 54.9444148179,
    "VarianceExplained": 0.0136262185
  },
  "w_comp_cor_08": {
    "CumulativeVarianceExplained": 0.1402337821,
    "Mask": "WM",
    "Method": "aCompCor",
    "Retained": true,
    "SingularValue": 54.6403279181,
    "VarianceExplained": 0.0134758088
  },
  "w_comp_cor_09": {
    "CumulativeVarianceExplained": 0.1536417843,
    "Mask": "WM",
    "Method": "aCompCor",
    "Retained": true,
    "SingularValue": 54.5026869063,
    "VarianceExplained": 0.0134080022
  },
  "w_comp_cor_10": {
    "CumulativeVarianceExplained": 0.1668648718,
    "Mask": "WM",
    "Method": "aCompCor",
    "Retained": true,
    "SingularValue": 54.1255488046,
    "VarianceExplained": 0.0132230875
  },
  "w_comp_cor_11": {
    "CumulativeVarianceExplained": 0.1799185401,
    "Mask": "WM",
    "Method": "aCompCor",
    "Retained": true,
    "SingularValue": 53.7776924849,
    "VarianceExplained": 0.0130536683
  },
  "w_comp_cor_12": {
    "CumulativeVarianceExplained": 0.1928575086,
    "Mask": "WM",
    "Method": "aCompCor",
    "Retained": true,
    "SingularValue": 53.5409046719,
    "VarianceExplained": 0.0129389685
  },
  "w_comp_cor_13": {
    "CumulativeVarianceExplained": 0.2056998854,
    "Mask": "WM",
    "Method": "aCompCor",
    "Retained": true,
    "SingularValue": 53.3406840933,
    "VarianceExplained": 0.0128423768
  },
  "w_comp_cor_14": {
    "CumulativeVarianceExplained": 0.2184826164,
    "Mask": "WM",
    "Method": "aCompCor",
    "Retained": true,
    "SingularValue": 53.2166708994,
    "VarianceExplained": 0.012782731
  },
  "w_comp_cor_15": {
    "CumulativeVarianceExplained": 0.2311635519,
    "Mask": "WM",
    "Method": "aCompCor",
    "Retained": true,
    "SingularValue": 53.004351214,
    "VarianceExplained": 0.0126809354
  },
  "w_comp_cor_16": {
    "CumulativeVarianceExplained": 0.2435884053,
    "Mask": "WM",
    "Method": "aCompCor",
    "Retained": true,
    "SingularValue": 52.466429943,
    "VarianceExplained": 0.0124248534
  },
  "w_comp_cor_17": {
    "CumulativeVarianceExplained": 0.2559139052,
    "Mask": "WM",
    "Method": "aCompCor",
    "Retained": true,
    "SingularValue": 52.2562388323,
    "VarianceExplained": 0.0123254999
  },
  "w_comp_cor_18": {
    "CumulativeVarianceExplained": 0.2681533757,
    "Mask": "WM",
    "Method": "aCompCor",
    "Retained": true,
    "SingularValue": 52.073550889,
    "VarianceExplained": 0.0122394706
  },
  "w_comp_cor_19": {
    "CumulativeVarianceExplained": 0.2802345183,
    "Mask": "WM",
    "Method": "aCompCor",
    "Retained": true,
    "SingularValue": 51.7356466471,
    "VarianceExplained": 0.0120811426
  },
  "w_comp_cor_20": {
    "CumulativeVarianceExplained": 0.2922325938,
    "Mask": "WM",
    "Method": "aCompCor",
    "Retained": true,
    "SingularValue": 51.5574788563,
    "VarianceExplained": 0.0119980755
  },
  "w_comp_cor_21": {
    "CumulativeVarianceExplained": 0.3040935136,
    "Mask": "WM",
    "Method": "aCompCor",
    "Retained": true,
    "SingularValue": 51.2619429767,
    "VarianceExplained": 0.0118609199
  },
  "w_comp_cor_22": {
    "CumulativeVarianceExplained": 0.3157853256,
    "Mask": "WM",
    "Method": "aCompCor",
    "Retained": true,
    "SingularValue": 50.8951955636,
    "VarianceExplained": 0.0116918119
  },
  "w_comp_cor_23": {
    "CumulativeVarianceExplained": 0.3273994029,
    "Mask": "WM",
    "Method": "aCompCor",
    "Retained": true,
    "SingularValue": 50.7257217163,
    "VarianceExplained": 0.0116140774
  },
  "w_comp_cor_24": {
    "CumulativeVarianceExplained": 0.3389177374,
    "Mask": "WM",
    "Method": "aCompCor",
    "Retained": true,
    "SingularValue": 50.5162053452,
    "VarianceExplained": 0.0115183345
  },
  "w_comp_cor_25": {
    "CumulativeVarianceExplained": 0.3504261372,
    "Mask": "WM",
    "Method": "aCompCor",
    "Retained": true,
    "SingularValue": 50.4944152987,
    "VarianceExplained": 0.0115083998
  },
  "w_comp_cor_26": {
    "CumulativeVarianceExplained": 0.3618331761,
    "Mask": "WM",
    "Method": "aCompCor",
    "Retained": true,
    "SingularValue": 50.2715572831,
    "VarianceExplained": 0.0114070389
  },
  "w_comp_cor_27": {
    "CumulativeVarianceExplained": 0.3731249369,
    "Mask": "WM",
    "Method": "aCompCor",
    "Retained": true,
    "SingularValue": 50.0168930933,
    "VarianceExplained": 0.0112917608
  },
  "w_comp_cor_28": {
    "CumulativeVarianceExplained": 0.3843637732,
    "Mask": "WM",
    "Method": "aCompCor",
    "Retained": true,
    "SingularValue": 49.8995409729,
    "VarianceExplained": 0.0112388363
  },
  "w_comp_cor_29": {
    "CumulativeVarianceExplained": 0.3954670655,
    "Mask": "WM",
    "Method": "aCompCor",
    "Retained": true,
    "SingularValue": 49.597725855,
    "VarianceExplained": 0.0111032923
  },
  "w_comp_cor_30": {
    "CumulativeVarianceExplained": 0.4064608166,
    "Mask": "WM",
    "Method": "aCompCor",
    "Retained": true,
    "SingularValue": 49.3524625253,
    "VarianceExplained": 0.0109937511
  },
  "w_comp_cor_31": {
    "CumulativeVarianceExplained": 0.4173771151,
    "Mask": "WM",
    "Method": "aCompCor",
    "Retained": true,
    "SingularValue": 49.1783074844,
    "VarianceExplained": 0.0109162985
  },
  "w_comp_cor_32": {
    "CumulativeVarianceExplained": 0.4281695053,
    "Mask": "WM",
    "Method": "aCompCor",
    "Retained": true,
    "SingularValue": 48.8984053694,
    "VarianceExplained": 0.0107923902
  },
  "w_comp_cor_33": {
    "CumulativeVarianceExplained": 0.4388744569,
    "Mask": "WM",
    "Method": "aCompCor",
    "Retained": true,
    "SingularValue": 48.6999182,
    "VarianceExplained": 0.0107049516
  },
  "w_comp_cor_34": {
    "CumulativeVarianceExplained": 0.4495430195,
    "Mask": "WM",
    "Method": "aCompCor",
    "Retained": true,
    "SingularValue": 48.6170756773,
    "VarianceExplained": 0.0106685626
  },
  "w_comp_cor_35": {
    "CumulativeVarianceExplained": 0.4601817839,
    "Mask": "WM",
    "Method": "aCompCor",
    "Retained": true,
    "SingularValue": 48.5491323362,
    "VarianceExplained": 0.0106387644
  },
  "w_comp_cor_36": {
    "CumulativeVarianceExplained": 0.4707221227,
    "Mask": "WM",
    "Method": "aCompCor",
    "Retained": true,
    "SingularValue": 48.3240319268,
    "VarianceExplained": 0.0105403388
  },
  "w_comp_cor_37": {
    "CumulativeVarianceExplained": 0.48117224,
    "Mask": "WM",
    "Method": "aCompCor",
    "Retained": true,
    "SingularValue": 48.1167692908,
    "VarianceExplained": 0.0104501173
  },
  "w_comp_cor_38": {
    "CumulativeVarianceExplained": 0.4915547356,
    "Mask": "WM",
    "Method": "aCompCor",
    "Retained": true,
    "SingularValue": 47.9608369848,
    "VarianceExplained": 0.0103824955
  },
  "w_comp_cor_39": {
    "CumulativeVarianceExplained": 0.5017864885,
    "Mask": "WM",
    "Method": "aCompCor",
    "Retained": true,
    "SingularValue": 47.6113943045,
    "VarianceExplained": 0.010231753
  },
  "white_matter": {
    "Method": "Mean"
  }
}